jsonld_recursive/__init__.py
jsonld_recursive/ldr_client.py
jsonld_recursive-1.0.0.dist-info/METADATA
jsonld_recursive-1.0.0.dist-info/WHEEL
jsonld_recursive-1.0.0.dist-info/top_level.txt
jsonld_recursive-1.0.0.dist-info/RECORD
