Metadata-Version: 2.4
Name: jsonld-recursive
Version: 1.0.0
Summary: Recursively expand and compact JSON-LD documents with caching and chained URL mappings
Author-email: Daniel Ellis <wolfiex@users.noreply.github.com>
License: MIT
Project-URL: Homepage, https://github.com/wolfiex/jsonld-recursive
Project-URL: Documentation, https://github.com/wolfiex/jsonld-recursive#readme
Project-URL: Repository, https://github.com/wolfiex/jsonld-recursive.git
Project-URL: Issues, https://github.com/wolfiex/jsonld-recursive/issues
Keywords: jsonld,json-ld,linked-data,semantic-web,expand,compact,recursive,rdf,cache,url-mapping,chained-mappings,wcrp,cmip
Classifier: Development Status :: 4 - Beta
Classifier: Intended Audience :: Developers
Classifier: License :: OSI Approved :: MIT License
Classifier: Programming Language :: Python :: 3
Classifier: Programming Language :: Python :: 3.7
Classifier: Programming Language :: Python :: 3.8
Classifier: Programming Language :: Python :: 3.9
Classifier: Programming Language :: Python :: 3.10
Classifier: Programming Language :: Python :: 3.11
Classifier: Programming Language :: Python :: 3.12
Classifier: Topic :: Software Development :: Libraries :: Python Modules
Classifier: Topic :: Internet :: WWW/HTTP
Classifier: Topic :: Text Processing :: Markup
Requires-Python: >=3.7
Requires-Dist: requests>=2.25.0
Requires-Dist: urllib3>=1.26.0
Provides-Extra: dev
Requires-Dist: pytest>=7.0.0; extra == "dev"
Requires-Dist: pytest-cov>=4.0.0; extra == "dev"
Requires-Dist: black>=22.0.0; extra == "dev"
Requires-Dist: flake8>=5.0.0; extra == "dev"
Requires-Dist: mypy>=0.990; extra == "dev"
